Workbook

Sheet Introduction
A1: KYC / AML Client Review - Self-Study Project (Beginner)
A2: Practice project for a Client Data Analyst (Operations) role. All data is synthetic.
A4: 1. Objective
A5: Learn the basic workflow of a KYC / AML review in Excel: (a) check whether each client's KYC file is complete and up to date, (b) rate each client's risk, and (c) screen transactions for simple AML red flags so you can say which clients need a closer look.
A7: 2. Necessary details
A8: Scenario | B8: 15 clients were onboarded and you have 3 months of their transactions (Jul-Sep 2026).
A9: Client_Data sheet | B9: Who the client is: ID, name, occupation, country, declared monthly income, and the risk rating (formula).
A10: KYC sheet | B10: What documents are on file: ID expiry date, address proof date, source of funds, plus status formulas.
A11: Transactions sheet | B11: What the client did: date, type, amount, counterparty country, plus red-flag formulas and an alert.
A12: Link between sheets | B12: Client ID is the common key. KYC and Transactions look up the client name from Client_Data.
A13: Colour code | B13: Blue text = a parameter you can change. Yellow cells = your own notes. Red / amber / green = automatic status colours.
A15: 3. Parameters used (the basis of the analysis)
A16: Parameter | B16: Value | C16: Used for
A17: Review (as-of) date | B17: 46299 | C17: Compared with ID expiry date and address proof date.
A18: Address proof valid for (days) | B18: 90 | C18: Address proof older than this is marked 'Old'.
A19: High-value threshold (INR) | B19: 1000000 | C19: Transactions at or above this are 'High Value'.
A20: Near-threshold band (% of threshold) | B20: 0.9 | C20: Amounts from this % up to the threshold look like structuring.
A22: High-risk countries | B22: Higher-risk occupations | C22: Why
A23: Iran | B23: Small Business Owner | C23: Country list is illustrative; real work uses the current FATF lists.
A24: Myanmar | B24: Real Estate Dealer | C24: Cash-heavy or high-value trades carry more laundering risk.
A25: North Korea | B25: Jeweller
B26: Import/Export Trader
A28: 4. Rules applied (how each result is decided)
A29: ID Status (KYC) | B29: Missing if no expiry date; Expired if expiry date is before the review date; otherwise Valid.
A30: Address Proof Status (KYC) | B30: Missing if blank; Old if older than the validity days; otherwise Valid.
A31: KYC Status | B31: Complete only if ID is Valid, address proof is Valid and a source of funds is given. Otherwise Action Required.
A32: Risk Rating (Client_Data) | B32: High if the country is on the high-risk list; Medium if the occupation is on the higher-risk list; otherwise Low.
A33: High Value? (Transactions) | B33: Yes if the amount is at or above the high-value threshold.
A34: Near Threshold? | B34: Yes if the amount is within the band just below the threshold (possible structuring - splitting deposits to stay under it).
A35: High-Risk Country? | B35: Yes if the counterparty country is on the high-risk list.
A36: Alert | B36: Review if any of the three flags is Yes; otherwise OK.
A37: Excel functions used | B37: IF, AND, COUNTIF, INDEX / MATCH only.

Sheet Client_Data
A1: Client ID | B1: Client Name | C1: Occupation | D1: Country | E1: Monthly Income (INR) | F1: Risk Rating
A2: C001 | B2: Aarav Mehta | C2: Salaried Employee | D2: India | E2: 85000 | F2: =IF(COUNTIF(Introduction!$A$23:$A$26,D2)>0,"High",IF(COUNTIF(Introduction!$B$23:$B$26,C2)>0,"Medium","Low")) -> Low
A3: C002 | B3: Priya Nair | C3: Salaried Employee | D3: India | E3: 62000 | F3: =IF(COUNTIF(Introduction!$A$23:$A$26,D3)>0,"High",IF(COUNTIF(Introduction!$B$23:$B$26,C3)>0,"Medium","Low")) -> Low
A4: C003 | B4: Rohan Deshpande | C4: Self-Employed Professional | D4: India | E4: 150000 | F4: =IF(COUNTIF(Introduction!$A$23:$A$26,D4)>0,"High",IF(COUNTIF(Introduction!$B$23:$B$26,C4)>0,"Medium","Low")) -> Low
A5: C004 | B5: Sneha Kulkarni | C5: Student | D5: India | E5: 15000 | F5: =IF(COUNTIF(Introduction!$A$23:$A$26,D5)>0,"High",IF(COUNTIF(Introduction!$B$23:$B$26,C5)>0,"Medium","Low")) -> Low
A6: C005 | B6: Vikram Singh | C6: Small Business Owner | D6: India | E6: 120000 | F6: =IF(COUNTIF(Introduction!$A$23:$A$26,D6)>0,"High",IF(COUNTIF(Introduction!$B$23:$B$26,C6)>0,"Medium","Low")) -> Medium
A7: C006 | B7: Ananya Iyer | C7: Salaried Employee | D7: Singapore | E7: 210000 | F7: =IF(COUNTIF(Introduction!$A$23:$A$26,D7)>0,"High",IF(COUNTIF(Introduction!$B$23:$B$26,C7)>0,"Medium","Low")) -> Low
A8: C007 | B8: Karan Malhotra | C8: Real Estate Dealer | D8: India | E8: 90000 | F8: =IF(COUNTIF(Introduction!$A$23:$A$26,D8)>0,"High",IF(COUNTIF(Introduction!$B$23:$B$26,C8)>0,"Medium","Low")) -> Medium
A9: C008 | B9: Fatima Sheikh | C9: Homemaker | D9: India | E9: 20000 | F9: =IF(COUNTIF(Introduction!$A$23:$A$26,D9)>0,"High",IF(COUNTIF(Introduction!$B$23:$B$26,C9)>0,"Medium","Low")) -> Low
A10: C009 | B10: Rajesh Gupta | C10: Jeweller | D10: India | E10: 300000 | F10: =IF(COUNTIF(Introduction!$A$23:$A$26,D10)>0,"High",IF(COUNTIF(Introduction!$B$23:$B$26,C10)>0,"Medium","Low")) -> Medium
A11: C010 | B11: Meera Joshi | C11: Retired | D11: India | E11: 45000 | F11: =IF(COUNTIF(Introduction!$A$23:$A$26,D11)>0,"High",IF(COUNTIF(Introduction!$B$23:$B$26,C11)>0,"Medium","Low")) -> Low
A12: C011 | B12: Arjun Reddy | C12: Import/Export Trader | D12: UAE | E12: 400000 | F12: =IF(COUNTIF(Introduction!$A$23:$A$26,D12)>0,"High",IF(COUNTIF(Introduction!$B$23:$B$26,C12)>0,"Medium","Low")) -> Medium
A13: C012 | B13: Sunita Bansal | C13: Small Business Owner | D13: India | E13: 80000 | F13: =IF(COUNTIF(Introduction!$A$23:$A$26,D13)>0,"High",IF(COUNTIF(Introduction!$B$23:$B$26,C13)>0,"Medium","Low")) -> Medium
... A16: C015 | B16: Shreya Pandey | C16: Salaried Employee | D16: India | E16: 58000 | F16: =IF(COUNTIF(Introduction!$A$23:$A$26,D16)>0,"High",IF(COUNTIF(Introduction!$B$23:$B$26,C16)>0,"Medium","Low")) -> Low

Sheet KYC
A1: Client ID | B1: Client Name | C1: ID Expiry Date | D1: Address Proof Date | E1: Source of Funds | F1: ID Status | G1: Address Proof Status | H1: KYC Status
A2: C001 | B2: =INDEX(Client_Data!$B$2:$B$16,MATCH(A2,Client_Data!$A$2:$A$16,0)) -> Aarav Mehta | C2: 47556 | D2: 46246 | E2: Salary | F2: =IF(C2="","Missing",IF(C2<Introduction!$B$17,"Expired","Valid")) -> Valid | G2: =IF(D2="","Missing",IF(Introduction!$B$17-D2>Introduction!$B$18,"Old","Valid")) -> Valid | H2: =IF(AND(F2="Valid",G2="Valid",E2<>""),"Complete","Action Required") -> Complete
A3: C002 | B3: =INDEX(Client_Data!$B$2:$B$16,MATCH(A3,Client_Data!$A$2:$A$16,0)) -> Priya Nair | C3: 47299 | D3: 46267 | E3: Salary | F3: =IF(C3="","Missing",IF(C3<Introduction!$B$17,"Expired","Valid")) -> Valid | G3: =IF(D3="","Missing",IF(Introduction!$B$17-D3>Introduction!$B$18,"Old","Valid")) -> Valid | H3: =IF(AND(F3="Valid",G3="Valid",E3<>""),"Complete","Action Required") -> Complete
A4: C003 | B4: =INDEX(Client_Data!$B$2:$B$16,MATCH(A4,Client_Data!$A$2:$A$16,0)) -> Rohan Deshpande | C4: 47077 | D4: 46228 | E4: Consulting fees | F4: =IF(C4="","Missing",IF(C4<Introduction!$B$17,"Expired","Valid")) -> Valid | G4: =IF(D4="","Missing",IF(Introduction!$B$17-D4>Introduction!$B$18,"Old","Valid")) -> Valid | H4: =IF(AND(F4="Valid",G4="Valid",E4<>""),"Complete","Action Required") -> Complete
A5: C004 | B5: =INDEX(Client_Data!$B$2:$B$16,MATCH(A5,Client_Data!$A$2:$A$16,0)) -> Sneha Kulkarni | C5: 46428 | D5: 46264 | E5: Parental support | F5: =IF(C5="","Missing",IF(C5<Introduction!$B$17,"Expired","Valid")) -> Valid | G5: =IF(D5="","Missing",IF(Introduction!$B$17-D5>Introduction!$B$18,"Old","Valid")) -> Valid | H5: =IF(AND(F5="Valid",G5="Valid",E5<>""),"Complete","Action Required") -> Complete
A6: C005 | B6: =INDEX(Client_Data!$B$2:$B$16,MATCH(A6,Client_Data!$A$2:$A$16,0)) -> Vikram Singh | C6: 46249 | D6: 46152 | E6: Retail shop income | F6: =IF(C6="","Missing",IF(C6<Introduction!$B$17,"Expired","Valid")) -> Expired | G6: =IF(D6="","Missing",IF(Introduction!$B$17-D6>Introduction!$B$18,"Old","Valid")) -> Old | H6: =IF(AND(F6="Valid",G6="Valid",E6<>""),"Complete","Action Required") -> Action Required
A7: C006 | B7: =INDEX(Client_Data!$B$2:$B$16,MATCH(A7,Client_Data!$A$2:$A$16,0)) -> Ananya Iyer | C7: 47853 | D7: 46280 | E7: Salary | F7: =IF(C7="","Missing",IF(C7<Introduction!$B$17,"Expired","Valid")) -> Valid | G7: =IF(D7="","Missing",IF(Introduction!$B$17-D7>Introduction!$B$18,"Old","Valid")) -> Valid | H7: =IF(AND(F7="Valid",G7="Valid",E7<>""),"Complete","Action Required") -> Complete
A8: C007 | B8: =INDEX(Client_Data!$B$2:$B$16,MATCH(A8,Client_Data!$A$2:$A$16,0)) -> Karan Malhotra | C8: 47370 | D8: 46235 | E8: Property commissions | F8: =IF(C8="","Missing",IF(C8<Introduction!$B$17,"Expired","Valid")) -> Valid | G8: =IF(D8="","Missing",IF(Introduction!$B$17-D8>Introduction!$B$18,"Old","Valid")) -> Valid | H8: =IF(AND(F8="Valid",G8="Valid",E8<>""),"Complete","Action Required") -> Complete
A9: C008 | B9: =INDEX(Client_Data!$B$2:$B$16,MATCH(A9,Client_Data!$A$2:$A$16,0)) -> Fatima Sheikh | C9: 46861 | D9: 46193 | E9: Spouse income | F9: =IF(C9="","Missing",IF(C9<Introduction!$B$17,"Expired","Valid")) -> Valid | G9: =IF(D9="","Missing",IF(Introduction!$B$17-D9>Introduction!$B$18,"Old","Valid")) -> Old | H9: =IF(AND(F9="Valid",G9="Valid",E9<>""),"Complete","Action Required") -> Action Required
A10: C009 | B10: =INDEX(Client_Data!$B$2:$B$16,MATCH(A10,Client_Data!$A$2:$A$16,0)) -> Rajesh Gupta | C10: 46722 | D10: 46275 | E10: Jewellery sales | F10: =IF(C10="","Missing",IF(C10<Introduction!$B$17,"Expired","Valid")) -> Valid | G10: =IF(D10="","Missing",IF(Introduction!$B$17-D10>Introduction!$B$18,"Old","Valid")) -> Valid | H10: =IF(AND(F10="Valid",G10="Valid",E10<>""),"Complete","Action Required") -> Complete
A11: C010 | B11: =INDEX(Client_Data!$B$2:$B$16,MATCH(A11,Client_Data!$A$2:$A$16,0)) -> Meera Joshi | C11: 46285 | D11: 46252 | E11: Pension | F11: =IF(C11="","Missing",IF(C11<Introduction!$B$17,"Expired","Valid")) -> Expired | G11: =IF(D11="","Missing",IF(Introduction!$B$17-D11>Introduction!$B$18,"Old","Valid")) -> Valid | H11: =IF(AND(F11="Valid",G11="Valid",E11<>""),"Complete","Action Required") -> Action Required
A12: C011 | B12: =INDEX(Client_Data!$B$2:$B$16,MATCH(A12,Client_Data!$A$2:$A$16,0)) -> Arjun Reddy | C12: 47671 | D12: 46256 | E12: Trading proceeds | F12: =IF(C12="","Missing",IF(C12<Introduction!$B$17,"Expired","Valid")) -> Valid | G12: =IF(D12="","Missing",IF(Introduction!$B$17-D12>Introduction!$B$18,"Old","Valid")) -> Valid | H12: =IF(AND(F12="Valid",G12="Valid",E12<>""),"Complete","Action Required") -> Complete
A13: C012 | B13: =INDEX(Client_Data!$B$2:$B$16,MATCH(A13,Client_Data!$A$2:$A$16,0)) -> Sunita Bansal | C13: 47180 | D13: 46270 | F13: =IF(C13="","Missing",IF(C13<Introduction!$B$17,"Expired","Valid")) -> Valid | G13: =IF(D13="","Missing",IF(Introduction!$B$17-D13>Introduction!$B$18,"Old","Valid")) -> Valid | H13: =IF(AND(F13="Valid",G13="Valid",E13<>""),"Complete","Action Required") -> Action Required
A14: C013 | B14: =INDEX(Client_Data!$B$2:$B$16,MATCH(A14,Client_Data!$A$2:$A$16,0)) -> Mohan Das | C14: 46463 | D14: 46170 | E14: Trading proceeds | F14: =IF(C14="","Missing",IF(C14<Introduction!$B$17,"Expired","Valid")) -> Valid | G14: =IF(D14="","Missing",IF(Introduction!$B$17-D14>Introduction!$B$18,"Old","Valid")) -> Old | H14: =IF(AND(F14="Valid",G14="Valid",E14<>""),"Complete","Action Required") -> Action Required
A15: C014 | B15: =INDEX(Client_Data!$B$2:$B$16,MATCH(A15,Client_Data!$A$2:$A$16,0)) -> Dev Chopra | C15: 46266 | D15: 46259 | E15: Restaurant income | F15: =IF(C15="","Missing",IF(C15<Introduction!$B$17,"Expired","Valid")) -> Expired | G15: =IF(D15="","Missing",IF(Introduction!$B$17-D15>Introduction!$B$18,"Old","Valid")) -> Valid | H15: =IF(AND(F15="Valid",G15="Valid",E15<>""),"Complete","Action Required") -> Action Required
A16: C015 | B16: =INDEX(Client_Data!$B$2:$B$16,MATCH(A16,Client_Data!$A$2:$A$16,0)) -> Shreya Pandey | D16: 46279 | E16: Salary | F16: =IF(C16="","Missing",IF(C16<Introduction!$B$17,"Expired","Valid")) -> Missing | G16: =IF(D16="","Missing",IF(Introduction!$B$17-D16>Introduction!$B$18,"Old","Valid")) -> Valid | H16: =IF(AND(F16="Valid",G16="Valid",E16<>""),"Complete","Action Required") -> Action Required

Sheet Transactions
A1: Txn ID | B1: Date | C1: Client ID | D1: Txn Type | E1: Amount (INR) | F1: Counterparty Country | G1: High Value? | H1: Near Threshold? | I1: High-Risk Country? | J1: Alert
A2: T001 | B2: 46204 | C2: C006 | D2: Salary Credit | E2: 210000 | F2: Singapore | G2: =IF(E2>=Introduction!$B$19,"Yes","No") -> No | H2: =IF(AND(E2>=Introduction!$B$19*Introduction!$B$20,E2<Introduction!$B$19),"Yes","No") -> No | I2: =IF(COUNTIF(Introduction!$A$23:$A$26,F2)>0,"Yes","No") -> No | J2: =IF(COUNTIF(G2:I2,"Yes")>0,"Review","OK") -> OK
A3: T002 | B3: 46204 | C3: C010 | D3: Pension Credit | E3: 45000 | F3: India | G3: =IF(E3>=Introduction!$B$19,"Yes","No") -> No | H3: =IF(AND(E3>=Introduction!$B$19*Introduction!$B$20,E3<Introduction!$B$19),"Yes","No") -> No | I3: =IF(COUNTIF(Introduction!$A$23:$A$26,F3)>0,"Yes","No") -> No | J3: =IF(COUNTIF(G3:I3,"Yes")>0,"Review","OK") -> OK
A4: T003 | B4: 46205 | C4: C001 | D4: Salary Credit | E4: 85000 | F4: India | G4: =IF(E4>=Introduction!$B$19,"Yes","No") -> No | H4: =IF(AND(E4>=Introduction!$B$19*Introduction!$B$20,E4<Introduction!$B$19),"Yes","No") -> No | I4: =IF(COUNTIF(Introduction!$A$23:$A$26,F4)>0,"Yes","No") -> No | J4: =IF(COUNTIF(G4:I4,"Yes")>0,"Review","OK") -> OK
A5: T004 | B5: 46205 | C5: C015 | D5: Salary Credit | E5: 58000 | F5: India | G5: =IF(E5>=Introduction!$B$19,"Yes","No") -> No | H5: =IF(AND(E5>=Introduction!$B$19*Introduction!$B$20,E5<Introduction!$B$19),"Yes","No") -> No | I5: =IF(COUNTIF(Introduction!$A$23:$A$26,F5)>0,"Yes","No") -> No | J5: =IF(COUNTIF(G5:I5,"Yes")>0,"Review","OK") -> OK
A6: T005 | B6: 46206 | C6: C002 | D6: Salary Credit | E6: 62000 | F6: India | G6: =IF(E6>=Introduction!$B$19,"Yes","No") -> No | H6: =IF(AND(E6>=Introduction!$B$19*Introduction!$B$20,E6<Introduction!$B$19),"Yes","No") -> No | I6: =IF(COUNTIF(Introduction!$A$23:$A$26,F6)>0,"Yes","No") -> No | J6: =IF(COUNTIF(G6:I6,"Yes")>0,"Review","OK") -> OK
A7: T006 | B7: 46208 | C7: C004 | D7: Bank Transfer In | E7: 15000 | F7: India | G7: =IF(E7>=Introduction!$B$19,"Yes","No") -> No | H7: =IF(AND(E7>=Introduction!$B$19*Introduction!$B$20,E7<Introduction!$B$19),"Yes","No") -> No | I7: =IF(COUNTIF(Introduction!$A$23:$A$26,F7)>0,"Yes","No") -> No | J7: =IF(COUNTIF(G7:I7,"Yes")>0,"Review","OK") -> OK
A8: T007 | B8: 46212 | C8: C014 | D8: Cash Deposit | E8: 130000 | F8: India | G8: =IF(E8>=Introduction!$B$19,"Yes","No") -> No | H8: =IF(AND(E8>=Introduction!$B$19*Introduction!$B$20,E8<Introduction!$B$19),"Yes","No") -> No | I8: =IF(COUNTIF(Introduction!$A$23:$A$26,F8)>0,"Yes","No") -> No | J8: =IF(COUNTIF(G8:I8,"Yes")>0,"Review","OK") -> OK
A9: T008 | B9: 46213 | C9: C005 | D9: Cash Deposit | E9: 110000 | F9: India | G9: =IF(E9>=Introduction!$B$19,"Yes","No") -> No | H9: =IF(AND(E9>=Introduction!$B$19*Introduction!$B$20,E9<Introduction!$B$19),"Yes","No") -> No | I9: =IF(COUNTIF(Introduction!$A$23:$A$26,F9)>0,"Yes","No") -> No | J9: =IF(COUNTIF(G9:I9,"Yes")>0,"Review","OK") -> OK
A10: T009 | B10: 46215 | C10: C011 | D10: Wire In | E10: 380000 | F10: UAE | G10: =IF(E10>=Introduction!$B$19,"Yes","No") -> No | H10: =IF(AND(E10>=Introduction!$B$19*Introduction!$B$20,E10<Introduction!$B$19),"Yes","No") -> No | I10: =IF(COUNTIF(Introduction!$A$23:$A$26,F10)>0,"Yes","No") -> No | J10: =IF(COUNTIF(G10:I10,"Yes")>0,"Review","OK") -> OK
A11: T010 | B11: 46218 | C11: C003 | D11: Wire In | E11: 150000 | F11: India | G11: =IF(E11>=Introduction!$B$19,"Yes","No") -> No | H11: =IF(AND(E11>=Introduction!$B$19*Introduction!$B$20,E11<Introduction!$B$19),"Yes","No") -> No | I11: =IF(COUNTIF(Introduction!$A$23:$A$26,F11)>0,"Yes","No") -> No | J11: =IF(COUNTIF(G11:I11,"Yes")>0,"Review","OK") -> OK
A12: T011 | B12: 46221 | C12: C012 | D12: Cash Deposit | E12: 70000 | F12: India | G12: =IF(E12>=Introduction!$B$19,"Yes","No") -> No | H12: =IF(AND(E12>=Introduction!$B$19*Introduction!$B$20,E12<Introduction!$B$19),"Yes","No") -> No | I12: =IF(COUNTIF(Introduction!$A$23:$A$26,F12)>0,"Yes","No") -> No | J12: =IF(COUNTIF(G12:I12,"Yes")>0,"Review","OK") -> OK
A13: T012 | B13: 46223 | C13: C009 | D13: Cash Deposit | E13: 280000 | F13: India | G13: =IF(E13>=Introduction!$B$19,"Yes","No") -> No | H13: =IF(AND(E13>=Introduction!$B$19*Introduction!$B$20,E13<Introduction!$B$19),"Yes","No") -> No | I13: =IF(COUNTIF(Introduction!$A$23:$A$26,F13)>0,"Yes","No") -> No | J13: =IF(COUNTIF(G13:I13,"Yes")>0,"Review","OK") -> OK
... A40: T039 | B40: 46281 | C40: C003 | D40: Wire In | E40: 155000 | F40: India | G40: =IF(E40>=Introduction!$B$19,"Yes","No") -> No | H40: =IF(AND(E40>=Introduction!$B$19*Introduction!$B$20,E40<Introduction!$B$19),"Yes","No") -> No | I40: =IF(COUNTIF(Introduction!$A$23:$A$26,F40)>0,"Yes","No") -> No | J40: =IF(COUNTIF(G40:I40,"Yes")>0,"Review","OK") -> OK
